triqs_hartree_fock/__init__.py
triqs_hartree_fock/impurity.py
triqs_hartree_fock/lattice.py
triqs_hartree_fock/utils.py
triqs_hartree_fock/version.py
hartree_fock-3.2.1.dist-info/COPYING.txt
hartree_fock-3.2.1.dist-info/LICENSE.txt
hartree_fock-3.2.1.dist-info/METADATA
hartree_fock-3.2.1.dist-info/WHEEL
hartree_fock-3.2.1.dist-info/top_level.txt
hartree_fock-3.2.1.dist-info/RECORD
